{
    "Fluid Dynamics": [
        {
            "name": "Reynolds Number",
            "formula": "Re = \\frac{\\rho v D}{\\mu}",
            "variables": {
                "ρ": "Density (kg/m³)",
                "v": "Flow velocity (m/s)",
                "D": "Characteristic length (m)",
                "μ": "Dynamic viscosity (Pa·s)"
            },
            "description": "Dimensionless number that predicts flow regime (laminar or turbulent)."
        },
        {
            "name": "Bernoulli's Equation",
            "formula": "P + \\frac{1}{2}\\rho v^2 + \\rho gh = \\text{constant}",
            "variables": {
                "P": "Pressure (Pa)",
                "ρ": "Density (kg/m³)",
                "v": "Velocity (m/s)",
                "g": "Gravitational acceleration (9.81 m/s²)",
                "h": "Height (m)"
            },
            "description": "Relates pressure, velocity, and elevation in a steady incompressible flow."
        },
        {
            "name": "Vector Differential Operator",
            "formula": "\\nabla = \\frac{\\partial }{\\partial x} \\bar{i} + \\frac{\\partial }{\\partial y} \\bar{j} + \\frac{\\partial }{\\partial z} \\bar{k}",
            "variables": {
                "P": "Pressure (Pa)",
                "ρ": "Density (kg/m³)",
                "v": "Velocity (m/s)",
                "g": "Gravitational acceleration (9.81 m/s²)",
                "h": "Height (m)"
            },
            "description": "Relates pressure, velocity, and elevation in a steady incompressible flow."
        },
        {
            "name": "Gradient of a scalar field (∇s)",
            "formula": "\\nabla s= \\frac{\\partial s}{\\partial x} \\bar{i} + \\frac{\\partial s}{\\partial y} \\bar{j} + \\frac{\\partial s}{\\partial z} \\bar{k}",
            "variables": {
                "P": "Pressure (Pa)",
                "ρ": "Density (kg/m³)",
                "v": "Velocity (m/s)",
                "g": "Gravitational acceleration (9.81 m/s²)",
                "h": "Height (m)"
            },
            "description": "Relates pressure, velocity, and elevation in a steady incompressible flow."
        },
        {
            "name": "Divergence of a vector field (∇.v)",
            "formula": "\\nabla .v= \\frac{\\partial v_{x}}{\\partial x} + \\frac{\\partial v_{y}}{\\partial y} + \\frac{\\partial v_{z}}{\\partial z}",
            "variables": {
                "Positive ∇∙v": "Indicates outward fluid flow",
                "∇∙v > 0": "The fluid flowing along the velocity vector field becomes less dense.",
                "∇∙v = 0": "The fluid is incompressible, then it can neither be a gain nor loss (Conservation of mass)"
            },
            "description": "∇∙v is a measure of the rate of loss of fluid per unit volume. It also measures the density fo fluid at every point."
        },
        {
            "name": "Divergence of the gradient of a scalar (∇.∇s)",
            "formula": "\\nabla .\\nabla s = \\nabla^2 s = \\frac{\\partial^2 s}{\\partial x^2} + \\frac{\\partial^2 s}{\\partial y^2} + \\frac{\\partial^2 s}{\\partial z^2}",
            "variables": {
                "Laplacian Operator": "The dot product of ∇ with itself.",
                "∇.∇": "The Laplacian operator has only the distributive property, just as the gradient and divergent."
            },
            "description": "The divergence of the gradient of a scalar function s in rectangular coordinates. The result is defined as the Laplacian of s."
        }
    ]
}